psusannx_pipeline/__init__.py
psusannx_pipeline/psusannx_pipeline.py
psusannx_pipeline-0.1.14.dist-info/LICENSE
psusannx_pipeline-0.1.14.dist-info/METADATA
psusannx_pipeline-0.1.14.dist-info/WHEEL
psusannx_pipeline-0.1.14.dist-info/top_level.txt
psusannx_pipeline-0.1.14.dist-info/RECORD
