Metadata-Version: 2.1
Name: psusannx-pipeline
Version: 0.1.14
Summary: A package containing classes to be used in the preprocessing data pipeline for the PSUSANNX project.
Author: Jamie O'Brien
Author-email: jamieob63@gmail.com
Project-URL: Source Code, https://github.com/jamieob63/psusannx_pipeline.git
Project-URL: Bug Tracker, https://github.com/jamieob63/psusannx_pipeline.git/issues
Requires-Python: ==3.*
License-File: LICENSE
Requires-Dist: numpy
Requires-Dist: pandas
Requires-Dist: scikit-learn
Requires-Dist: category-encoders (>=2.2.2)
